smobot_api/__init__.py
smobot_api/__main__.py
smobot_api/smobot_api.py
smobot_api-0.0.4.dist-info/LICENSE.txt
smobot_api-0.0.4.dist-info/METADATA
smobot_api-0.0.4.dist-info/WHEEL
smobot_api-0.0.4.dist-info/top_level.txt
smobot_api-0.0.4.dist-info/RECORD
