Metadata-Version: 2.1
Name: smobot-api
Version: 0.0.4
Summary: Pull data for your Smobot Controller
Home-page: https://github.com/adam-mckee/smobot_api
Author: adam-mckee
Author-email: invalid@example.org
License: GPLv3
Keywords: smobot_api
Classifier: Development Status :: 3 - Alpha
Classifier: Intended Audience :: Developers
Classifier: License :: OSI Approved :: MIT License
Classifier: Programming Language :: Python :: 3
License-File: LICENSE.txt
Requires-Dist: asyncio
Requires-Dist: aiohttp
